python_appimage/__init__.py
python_appimage/__main__.py
python_appimage/version.py
python_appimage/appimage/__init__.py
python_appimage/appimage/appify.py
python_appimage/appimage/build.py
python_appimage/appimage/relocate.py
python_appimage/commands/__init__.py
python_appimage/commands/install.py
python_appimage/commands/list.py
python_appimage/commands/which.py
python_appimage/commands/build/__init__.py
python_appimage/commands/build/app.py
python_appimage/commands/build/local.py
python_appimage/commands/build/manylinux.py
python_appimage/commands/cache/__init__.py
python_appimage/commands/cache/clean.py
python_appimage/commands/cache/get.py
python_appimage/commands/cache/list.py
python_appimage/data/LICENSE
python_appimage/data/_initappimage.py
python_appimage/data/apprun.sh
python_appimage/data/entrypoint.sh
python_appimage/data/python-wrapper.sh
python_appimage/data/python.appdata.xml
python_appimage/data/python.desktop
python_appimage/data/python.png
python_appimage/data/sitecustomize.py
python_appimage/manylinux/__init__.py
python_appimage/manylinux/config.py
python_appimage/manylinux/download.py
python_appimage/manylinux/extract.py
python_appimage/manylinux/patch.py
python_appimage/utils/__init__.py
python_appimage/utils/compat.py
python_appimage/utils/deps.py
python_appimage/utils/fs.py
python_appimage/utils/log.py
python_appimage/utils/manylinux.py
python_appimage/utils/system.py
python_appimage/utils/template.py
python_appimage/utils/tmp.py
python_appimage/utils/url.py
python_appimage/utils/version.py
python_appimage-1.4.5.dist-info/licenses/LICENSE
python_appimage-1.4.5.dist-info/METADATA
python_appimage-1.4.5.dist-info/WHEEL
python_appimage-1.4.5.dist-info/entry_points.txt
python_appimage-1.4.5.dist-info/top_level.txt
python_appimage-1.4.5.dist-info/RECORD
