Metadata-Version: 2.4
Name: python_appimage
Version: 1.4.5
Summary: Appimage releases of Python
Author-email: Valentin Niess <valentin.niess@gmail.com>
License-Expression: GPL-3.0-or-later
Project-URL: homepage, https://github.com/niess/python-appimage
Project-URL: documentation, https://python-appimage.readthedocs.io
Project-URL: download, https://pypi.python.org/pypi/python-appimage
Project-URL: source, https://github.com/niess/python-appimage
Project-URL: issues, https://github.com/niess/python-appimage/issues
Classifier: Development Status :: 4 - Beta
Classifier: Intended Audience :: Developers
Classifier: Programming Language :: Python
Classifier: Topic :: Software Development
Classifier: Operating System :: POSIX :: Linux
Requires-Python: >=3.9
License-File: LICENSE
Requires-Dist: requests
Requires-Dist: setuptools
Dynamic: license-file
